mypythonlib/__init__.py
mypythonlib/myfunctions.py
mypythonlib007-0.1.0.dist-info/METADATA
mypythonlib007-0.1.0.dist-info/WHEEL
mypythonlib007-0.1.0.dist-info/top_level.txt
mypythonlib007-0.1.0.dist-info/RECORD
